import_me/__init__.py
import_me/columns.py
import_me/constants.py
import_me/exceptions.py
import_me/processors.py
import_me/parsers/__init__.py
import_me/parsers/base.py
import_me/parsers/csv.py
import_me/parsers/xlsx.py
tests/__init__.py
tests/conftest.py
tests/test_columns.py
tests/test_exceptions.py
tests/test_processors.py
tests/test_parsers/__init__.py
tests/test_parsers/test_base.py
tests/test_parsers/test_csv.py
tests/test_parsers/test_xlsx.py
import_me-0.3.1.dist-info/LICENSE
import_me-0.3.1.dist-info/METADATA
import_me-0.3.1.dist-info/WHEEL
import_me-0.3.1.dist-info/top_level.txt
import_me-0.3.1.dist-info/RECORD
