Metadata-Version: 2.1
Name: import-me
Version: 0.3.1
Summary: Python tool for importing and validating data from xlsx/xls/csv files.
Home-page: https://github.com/best-doctor/import_me
Author: Ilya Lebedev
Author-email: melevir@gmail.com
License: MIT
Keywords: xlsx csv import
Platform: UNKNOWN
Classifier: Environment :: Console
Classifier: Operating System :: OS Independent
Classifier: Topic :: Software Development :: Libraries :: Python Modules
Classifier: Programming Language :: Python
Classifier: Programming Language :: Python :: 3.7
Classifier: Programming Language :: Python :: 3.8
Classifier: Programming Language :: Python :: 3.9
License-File: LICENSE
Requires-Dist: setuptools
Requires-Dist: openpyxl (>=3.0.1)
Requires-Dist: xlrd (>=1.2.0)
Requires-Dist: email-validator (>=1.0.5)
